tutle/__init__.py
tutle/tutle.py
tutle-1.2.2.dist-info/LICENCE
tutle-1.2.2.dist-info/METADATA
tutle-1.2.2.dist-info/WHEEL
tutle-1.2.2.dist-info/top_level.txt
tutle-1.2.2.dist-info/RECORD
